tiltx/__init__.py
tiltx/data_generator.py
tiltx/feature_extractor.py
tiltx/version.py
tiltx/support/__init__.py
tiltx/support/methods.py
tiltx-0.0.1.dist-info/LICENSE
tiltx-0.0.1.dist-info/METADATA
tiltx-0.0.1.dist-info/WHEEL
tiltx-0.0.1.dist-info/top_level.txt
tiltx-0.0.1.dist-info/RECORD
