Metadata-Version: 2.1
Name: tiltx
Version: 0.0.1
Summary: Feature extraction from mobile phone motion sensor data
Home-page: https://github.com/marses/tiltx
Author: Marko Seslija
Author-email: marko.seslija@gmail.com
License: UNKNOWN
Platform: UNKNOWN
Classifier: Programming Language :: Python :: 3
Classifier: License :: OSI Approved :: MIT License
Requires-Python: >=3.6
